nova_net/__init__.py
nova_net/datasets.py
nova_net/inference.py
nova_net/model.py
nova_net/setup.py
nova_net/train.py
nova_net/transforms.py
nova_net/utils.py
nova_net-0.1.0.dist-info/METADATA
nova_net-0.1.0.dist-info/WHEEL
nova_net-0.1.0.dist-info/top_level.txt
nova_net-0.1.0.dist-info/RECORD
